MANIFEST.in
README.rst
setup.py
docs/HISTORY.txt
docs/LICENSE.GPL
docs/LICENSE.txt
ftw/__init__.py
ftw.blueprints.egg-info/PKG-INFO
ftw.blueprints.egg-info/SOURCES.txt
ftw.blueprints.egg-info/dependency_links.txt
ftw.blueprints.egg-info/entry_points.txt
ftw.blueprints.egg-info/namespace_packages.txt
ftw.blueprints.egg-info/not-zip-safe
ftw.blueprints.egg-info/requires.txt
ftw.blueprints.egg-info/top_level.txt
ftw/blueprints/__init__.py
ftw/blueprints/configure.zcml
ftw/blueprints/handlers.py
ftw/blueprints/interfaces.py
ftw/blueprints/testing.py
ftw/blueprints/example/__init__.py
ftw/blueprints/example/archetypes.cfg
ftw/blueprints/example/configure.zcml
ftw/blueprints/example/dexterity.cfg
ftw/blueprints/example/pfm2pfg.cfg
ftw/blueprints/sections/__init__.py
ftw/blueprints/sections/annotate.py
ftw/blueprints/sections/configure.zcml
ftw/blueprints/sections/encapsulator.py
ftw/blueprints/sections/inserter.py
ftw/blueprints/sections/logger.py
ftw/blueprints/sections/mapper.py
ftw/blueprints/sections/multilingual.py
ftw/blueprints/sections/pfm2pfg.py
ftw/blueprints/sections/portlet.py
ftw/blueprints/sections/position.py
ftw/blueprints/sections/updater.py
ftw/blueprints/sections/workflow.py
ftw/blueprints/tests/__init__.py
ftw/blueprints/tests/base.py
ftw/blueprints/tests/test_additional_object_inserter.py
ftw/blueprints/tests/test_encapsulator.py
ftw/blueprints/tests/test_field_mapper.py
ftw/blueprints/tests/test_multilingual.py
ftw/blueprints/tests/test_path_mapper.py
ftw/blueprints/tests/test_portlet.py
ftw/blueprints/tests/test_position.py
ftw/blueprints/tests/test_type_field_mapper.py
ftw/blueprints/tests/test_workflow.py
ftw/blueprints/tests/test_xml_handler.py
ftw/blueprints/tests/utils.py