Metadata-Version: 1.1
Name: ftw.blueprints
Version: 1.0.0
Summary: Provides useful blueprints for migrations with transmogrifier
Home-page: https://github.com/4teamwork/ftw.blueprints
Author: 4teamwork AG
Author-email: mailto:info@4teamwork.ch
License: GPL2
Platform: UNKNOWN
Classifier: Framework :: Plone
Classifier: Framework :: Plone :: 4.2
Classifier: Framework :: Plone :: 4.3
Classifier: Intended Audience :: Developers
Classifier: Topic :: Software Development :: Libraries :: Python Modules
